oal/__init__.py
oal/__main__.py
oal/_compat.py
oal/log.py
oal/oal.py
oal-0.5.0.dist-info/DESCRIPTION.rst
oal-0.5.0.dist-info/METADATA
oal-0.5.0.dist-info/RECORD
oal-0.5.0.dist-info/WHEEL
oal-0.5.0.dist-info/entry_points.txt
oal-0.5.0.dist-info/metadata.json
oal-0.5.0.dist-info/top_level.txt
