Metadata-Version: 2.0
Name: oal
Version: 0.5.0
Summary: Office 365 Address Lists
Home-page: https://github.com/napalm255/oal
Author: Brad Gibson
Author-email: napalm255@gmail.com
License: BSD license
Keywords: oal
Platform: UNKNOWN
Classifier: Development Status :: 2 - Pre-Alpha
Classifier: Intended Audience :: Developers
Classifier: License :: OSI Approved :: BSD License
Classifier: Natural Language :: English
Classifier: Programming Language :: Python :: 2
Classifier: Programming Language :: Python :: 2.6
Classifier: Programming Language :: Python :: 2.7
Classifier: Programming Language :: Python :: 3
Classifier: Programming Language :: Python :: 3.3
Classifier: Programming Language :: Python :: 3.4
Classifier: Programming Language :: Python :: 3.5
Requires-Dist: click (==6.6)
Requires-Dist: ipaddress (==1.0.17)
Requires-Dist: requests (==2.11.1)
